mu_invenio_cli/__init__.py
mu_invenio_cli/cli_context.py
mu_invenio_cli/draft_selector.py
mu_invenio_cli/file_selector.py
mu_invenio_cli/help_messages.py
mu_invenio_cli/main.py
mu_invenio_cli/services/__init__.py
mu_invenio_cli/services/file_service.py
mu_invenio_cli/services/record_service.py
mu_invenio_cli/states/__init__.py
mu_invenio_cli/states/base_state.py
mu_invenio_cli/states/batch_create_state.py
mu_invenio_cli/states/configuration_state.py
mu_invenio_cli/states/create_state.py
mu_invenio_cli/states/delete_state.py
mu_invenio_cli/states/helper_state.py
mu_invenio_cli/states/not_selected_state.py
mu_invenio_cli/states/selected_state.py
mu_invenio_cli/states/state.py
mu_invenio_cli/uploaders/__init__.py
mu_invenio_cli/uploaders/base_uploader.py
mu_invenio_cli/uploaders/file_uploader.py
mu_invenio_cli/uploaders/multipart_uploader.py
mu_invenio_cli-2.1.0.dist-info/licenses/AUTHORS.rst
mu_invenio_cli-2.1.0.dist-info/licenses/LICENSE
tests/__init__.py
tests/test_cli_uni.py
tests/test_run.py
mu_invenio_cli-2.1.0.dist-info/METADATA
mu_invenio_cli-2.1.0.dist-info/WHEEL
mu_invenio_cli-2.1.0.dist-info/entry_points.txt
mu_invenio_cli-2.1.0.dist-info/top_level.txt
mu_invenio_cli-2.1.0.dist-info/RECORD
