Metadata-Version: 2.4
Name: mu_invenio_cli
Version: 2.1.0
Summary: Invenio Command Line Interface
Home-page: https://gitlab.ics.muni.cz/dataraptors/elter/dar-cli
Author: Dominik Dubovsky <485020@mail.muni.cz>
License: MIT
Project-URL: Source, https://gitlab.ics.muni.cz/dataraptors/elter/dar-cli
Requires-Python: >=3.10
License-File: LICENSE
License-File: AUTHORS.rst
Requires-Dist: requests
Requires-Dist: asyncio
Requires-Dist: aiohttp
Dynamic: license-file
